jogseq/__init__.py
jogseq/tasks/__init__.py
jogseq/tasks/seq.py
jogseq/utils/__init__.py
jogseq/utils/duration.py
jogseq/utils/jira.py
jogseq/utils/logseq.py
task_jogger_jogseq-0.4.0.dist-info/LICENSE
task_jogger_jogseq-0.4.0.dist-info/METADATA
task_jogger_jogseq-0.4.0.dist-info/WHEEL
task_jogger_jogseq-0.4.0.dist-info/top_level.txt
task_jogger_jogseq-0.4.0.dist-info/RECORD
