Metadata-Version: 2.1
Name: task-jogger-jogseq
Version: 0.4.0
Summary: A plugin for jogger that provides an interactive synchronisation tool for Logseq and Jira
Home-page: https://github.com/oogles/task-jogger-jogseq
Author: Alex Church
Author-email: alex@church.id.au
License: MIT
Project-URL: Bug Tracker, https://github.com/oogles/task-jogger-jogseq/issues
Classifier: Intended Audience :: Developers
Classifier: License :: OSI Approved :: MIT License
Classifier: Operating System :: OS Independent
Classifier: Programming Language :: Python :: 3
Requires-Python: >=3.6
License-File: LICENSE
Requires-Dist: task-jogger >=1.1.1
Requires-Dist: jira >=3.5.2
